[{
        "id": 1,
        "listed_by": 1,
        "jobTitle": "Head Worker",
        "jobDescript": "We need people to work hard!",
        "jobWage": "10000",
        "jobLocation": "South Austrlia",
        "workLoad": "Casual",
        "industry": "IT",
        "experience": "1 year",
        "qualification": "Graduate"
    },
    {
        "id": 2,
        "listed_by": 2,
        "jobTitle": "Night Shift Manager",
        "jobDescript": "We need people to work night work!",
        "jobWage": "15000",
        "jobLocation": "Melbourne",
        "workLoad": "Casual",
        "industry": "Mining",
        "experience": "2 years",
        "qualification": "No qualification"
    },
    {
        "id": 3,
        "listed_by": 3,
        "jobTitle": "Day Logistics Manager",
        "jobDescript": "We need people to work during the day!",
        "jobWage": "20000",
        "jobLocation": "Tasmania",
        "workLoad": "Full Time",
        "industry": "Construction",
        "experience": "3 years",
        "qualification": "Bachelor Degree"
    }
]